{
  "catalog": [
    {
      "name": "Forecast Models",
      "type": "group",
      "items": [
        {
          "name": "ASGS Sandy29 sci-wms",
          "type": "wms",
          "url": "http://gamone.whoi.edu/wms/datasets/asgs_sandy_29",
          "isEnabled": true,
          "layers": "zeta",
          "colorScaleMinimum": -1.0,
          "colorScaleMaximum": 5.0,
          "initialTimeSource": "2012-10-30T02:00:00Z",
          "styles": "filledcontours_cubehelix",
          "parameters": {
            "VERSION": "1.1.1"
            }
        },
        {
          "name": "ASGS Sandy29 ncWMS2",
          "type": "wms",
          "url": "http://gamone.whoi.edu/ncWMS/wms",
          "isEnabled": true,
          "layers": "ASGS-Sandy-29/zeta",
          "colorScaleMinimum": -1.0,
          "colorScaleMaximum": 5.0,
          "initialTimeSource": "2012-10-30T02:00:00Z",
          "styles": "default-scalar/default",
          "parameters": {
            "VERSION": "1.1.1"
             }
        }
      ],
      "isOpen": true
    }
  ],
  "corsDomains": [
    "whoi.edu",
    "corsproxy.com",
    "programs.communications.gov.au",
    "www.asris.csiro.au"
  ],
  "homeCamera": {
    "west": -71.5,
    "east": -65,
    "north": 45.0,
    "south": 39.0
  },
  "baseMapName": "Bing Maps Roads",
  "initialViewerMode": "2d",
  "services": []
}
